README.rst
setup.py
aiosocks/__init__.py
aiosocks/connector.py
aiosocks/constants.py
aiosocks/errors.py
aiosocks/helpers.py
aiosocks/protocols.py
aiosocks/test_utils.py
aiosocks.egg-info/PKG-INFO
aiosocks.egg-info/SOURCES.txt
aiosocks.egg-info/dependency_links.txt
aiosocks.egg-info/top_level.txt