Metadata-Version: 1.0
Name: aiosocks
Version: 0.2.2
Summary: SOCKS proxy client for asyncio and aiohttp
Home-page: https://github.com/nibrag/aiosocks
Author: Nail Ibragimov
Author-email: ibragwork@gmail.com
License: Apache 2
Platform: UNKNOWN
